res_return.py
mcp_getting_started-0.1.0.dist-info/METADATA
mcp_getting_started-0.1.0.dist-info/WHEEL
mcp_getting_started-0.1.0.dist-info/entry_points.txt
mcp_getting_started-0.1.0.dist-info/top_level.txt
mcp_getting_started-0.1.0.dist-info/RECORD
