Metadata-Version: 2.4
Name: mcp-getting-started
Version: 0.1.0
Summary: Add your description here
Requires-Python: >=3.13
Requires-Dist: httpx>=0.28.1
Requires-Dist: mcp[cli]>=1.17.0
Requires-Dist: openai>=2.3.0
